pyrusquant/__init__.py
pyrusquant/async_parsing.py
pyrusquant/services/__init__.py
pyrusquant/services/gigapack.py
rusquant-0.1.2.dist-info/LICENSE
rusquant-0.1.2.dist-info/METADATA
rusquant-0.1.2.dist-info/WHEEL
rusquant-0.1.2.dist-info/top_level.txt
rusquant-0.1.2.dist-info/RECORD
