Metadata-Version: 2.1
Name: rusquant
Version: 0.1.2
Summary: Quantitative Trading Framework
Home-page: https://github.com/arbuzovv/rusquant
Author: V.Arbuzov
Author-email: arbuzov1989@gmail.com
License: MIT
Classifier: Programming Language :: Python :: 3
Classifier: License :: OSI Approved :: MIT License
Classifier: Operating System :: OS Independent
Requires-Python: >=3.6
License-File: LICENSE
Requires-Dist: requests
